djmicrosip_exportadb
